{
    "ACH32_00": {
        "earned": true,
        "earned_time": 1363092170
    },
    "ACH33_00": {
        "earned": true,
        "earned_time": 1363092169
    },
    "ACH34_00": {
        "earned": true,
        "earned_time": 1363092169
    },
    "ACH35_00": {
        "earned": false,
        "earned_time": 0
    },
    "ACH36_00": {
        "earned": true,
        "earned_time": 1363092169
    },
    "ACH37_00": {
        "earned": true,
        "earned_time": 1363092169
    },
    "ACH38_00": {
        "earned": true,
        "earned_time": 1363092169
    },
    "ACH39_00": {
        "earned": true,
        "earned_time": 1363092169
    },
    "ACH40_00": {
        "earned": true,
        "earned_time": 1363092169
    },
    "XP2ACH01_00": {
        "earned": true,
        "earned_time": 1363092168
    },
    "XP2ACH02_00": {
        "earned": true,
        "earned_time": 1363092168
    },
    "XP2ACH03_00": {
        "earned": true,
        "earned_time": 1363092168
    },
    "XP2ACH04_00": {
        "earned": true,
        "earned_time": 1363092168
    },
    "XP2ACH05_00": {
        "earned": false,
        "earned_time": 0
    },
    "XP3ACH01_00": {
        "earned": true,
        "earned_time": 1363092168
    },
    "XP3ACH02_00": {
        "earned": true,
        "earned_time": 1363092168
    },
    "XP3ACH03_00": {
        "earned": false,
        "earned_time": 0
    },
    "XP3ACH04_00": {
        "earned": false,
        "earned_time": 0
    },
    "XP3ACH05_00": {
        "earned": false,
        "earned_time": 0
    },
    "XP4ACH01_00": {
        "earned": false,
        "earned_time": 0
    },
    "XP4ACH02_00": {
        "earned": true,
        "earned_time": 1363092168
    },
    "XP4ACH03_00": {
        "earned": true,
        "earned_time": 1371234425
    },
    "XP4ACH04_00": {
        "earned": false,
        "earned_time": 0
    },
    "XP4ACH05_00": {
        "earned": false,
        "earned_time": 0
    },
    "XP5ACH01_00": {
        "earned": true,
        "earned_time": 1371231423
    },
    "XP5ACH02_00": {
        "earned": false,
        "earned_time": 0
    },
    "XP5ACH03_00": {
        "earned": true,
        "earned_time": 1363108764
    },
    "XP5ach04_00": {
        "earned": false,
        "earned_time": 0
    },
    "XP5ach05_00": {
        "earned": false,
        "earned_time": 0
    },
    "XPACH01_00": {
        "earned": false,
        "earned_time": 0
    },
    "XPACH02_00": {
        "earned": true,
        "earned_time": 1363092169
    },
    "XPACH03_00": {
        "earned": false,
        "earned_time": 0
    },
    "XPACH04_00": {
        "earned": false,
        "earned_time": 0
    },
    "XPACH05_00": {
        "earned": true,
        "earned_time": 1363092168
    }
}