{
  "GRWildlands_Ach_1": {
    "earned": true,
    "earned_time": 1498851639
  },
  "GRWildlands_Ach_2": {
    "earned": true,
    "earned_time": 1498227701
  },
  "GRWildlands_Ach_3": {
    "earned": true,
    "earned_time": 1498824826
  },
  "GRWildlands_Ach_4": {
    "earned": true,
    "earned_time": 1499075436
  },
  "GRWildlands_Ach_5": {
    "earned": true,
    "earned_time": 1498843702
  },
  "GRWildlands_Ach_6": {
    "earned": true,
    "earned_time": 1500055350
  },
  "GRWildlands_Ach_7": {
    "earned": true,
    "earned_time": 1498146277
  },
  "GRWildlands_Ach_8": {
    "earned": true,
    "earned_time": 1500036073
  },
  "GRWildlands_Ach_9": {
    "earned": true,
    "earned_time": 1500032523
  },
  "GRWildlands_Ach_10": {
    "earned": true,
    "earned_time": 1500059085
  },
  "GRWildlands_Ach_11": {
    "earned": true,
    "earned_time": 1500057872
  },
  "GRWildlands_Ach_12": {
    "earned": true,
    "earned_time": 1498935421
  },
  "GRWildlands_Ach_13": {
    "earned": true,
    "earned_time": 1500059336
  },
  "GRWildlands_Ach_14": {
    "earned": true,
    "earned_time": 1498154477
  },
  "GRWildlands_Ach_15": {
    "earned": true,
    "earned_time": 1498144137
  },
  "GRWildlands_Ach_16": {
    "earned": true,
    "earned_time": 1498132998
  },
  "GRWildlands_Ach_17": {
    "earned": true,
    "earned_time": 1498148881
  },
  "GRWildlands_Ach_18": {
    "earned": true,
    "earned_time": 1498479534
  },
  "GRWildlands_Ach_19": {
    "earned": true,
    "earned_time": 1499526321
  },
  "GRWildlands_Ach_20": {
    "earned": true,
    "earned_time": 1499526095
  },
  "GRWildlands_Ach_21": {
    "earned": true,
    "earned_time": 1498143365
  },
  "GRWildlands_Ach_22": {
    "earned": true,
    "earned_time": 1500050095
  },
  "GRWildlands_Ach_23": {
    "earned": true,
    "earned_time": 1498222328
  },
  "GRWildlands_Ach_24": {
    "earned": true,
    "earned_time": 1498246863
  },
  "GRWildlands_Ach_25": {
    "earned": true,
    "earned_time": 1499073187
  },
  "GRWildlands_Ach_26": {
    "earned": true,
    "earned_time": 1500054496
  },
  "GRWildlands_Ach_27": {
    "earned": true,
    "earned_time": 1499544722
  },
  "GRWildlands_Ach_28": {
    "earned": true,
    "earned_time": 1500051155
  },
  "GRWildlands_Ach_29": {
    "earned": true,
    "earned_time": 1497865604
  },
  "GRWildlands_Ach_30": {
    "earned": true,
    "earned_time": 1498222325
  },
  "GRWildlands_Ach_31": {
    "earned": true,
    "earned_time": 1499023349
  },
  "GRWildlands_Ach_32": {
    "earned": true,
    "earned_time": 1500036075
  },
  "GRWildlands_Ach_33": {
    "earned": true,
    "earned_time": 1500054285
  },
  "GRWildlands_Ach_34": {
    "earned": true,
    "earned_time": 1499002118
  },
  "GRWildlands_Ach_35": {
    "earned": true,
    "earned_time": 1498852629
  },
  "GRWildlands_Ach_36": {
    "earned": true,
    "earned_time": 1498143153
  },
  "GRWildlands_Ach_37": {
    "earned": true,
    "earned_time": 1498152575
  },
  "GRWildlands_Ach_38": {
    "earned": true,
    "earned_time": 1498844789
  },
  "GRWildlands_Ach_39": {
    "earned": true,
    "earned_time": 1498841123
  },
  "GRWildlands_Ach_40": {
    "earned": true,
    "earned_time": 1500048311
  },
  "GRWildlands_Ach_41": {
    "earned": true,
    "earned_time": 1499549035
  },
  "GRWildlands_Ach_42": {
    "earned": true,
    "earned_time": 1499691654
  },
  "GRWildlands_Ach_43": {
    "earned": true,
    "earned_time": 1500053837
  },
  "GRWildlands_Ach_44": {
    "earned": true,
    "earned_time": 1500566420
  },
  "GRWildlands_Ach_45": {
    "earned": true,
    "earned_time": 1501104267
  },
  "GRWildlands_Ach_46": {
    "earned": true,
    "earned_time": 1501187792
  },
  "GRWildlands_Ach_47": {
    "earned": true,
    "earned_time": 1501020965
  },
  "GRWildlands_Ach_48": {
    "earned": true,
    "earned_time": 1501189295
  },
  "GRWildlands_Ach_49": {
    "earned": true,
    "earned_time": 1500471918
  },
  "GRWildlands_Ach_50": {
    "earned": true,
    "earned_time": 1500469702
  },
  "GRWildlands_Ach_51": {
    "earned": true,
    "earned_time": 1500068847
  },
  "GRWildlands_Ach_52": {
    "earned": true,
    "earned_time": 1500387626
  },
  "GRWildlands_Ach_53": {
    "earned": true,
    "earned_time": 1500391802
  },
  "GRWildlands_Ach_54": {
    "earned": true,
    "earned_time": 1500388849
  },
  "GRWildlands_Ach_55": {
    "earned": true,
    "earned_time": 1500232097
  },
  "GRWildlands_Ach_56": {
    "earned": true,
    "earned_time": 1500234929
  },
  "GRWildlands_Ach_57": {
    "earned": true,
    "earned_time": 1500228605
  }
}
